[
  {
    "id": 1,
    "firstName": "Tuvshin-Erdene",
    "lastName": "Erdenebat",
    "mobile": "99******",
    "email": "tuvshin.erdene25@gmail.com"
  },
  {
    "id": 2,
    "firstName": "Altan",
    "lastName": "Batbayar",
    "mobile": "88******",
    "email": "altan.batbayar@gmail.com"
  },
  {
    "id": 3,
    "firstName": "Nomin",
    "lastName": "Tserendorj",
    "mobile": "95******",
    "email": "nomin.tseren@example.com"
  },
  {
    "id": 4,
    "firstName": "Bat-Erdene",
    "lastName": "Chuluun",
    "mobile": "94******",
    "email": "bat.erdene1998@mail.com"
  },
  {
    "id": 5,
    "firstName": "Enkhjin",
    "lastName": "Ganbold",
    "mobile": "85******",
    "email": "enkhjin.ganbold@yahoo.com"
  },
  {
    "id": 6,
    "firstName": "Tsolmon",
    "lastName": "Davaadorj",
    "mobile": "96******",
    "email": "tsolmon.davaa@gmail.com"
  },
  {
    "id": 7,
    "firstName": "Erkhembayar",
    "lastName": "Sukhbaatar",
    "mobile": "90******",
    "email": "erkhem.sukh@example.com"
  },
  {
    "id": 8,
    "firstName": "Solongo",
    "lastName": "Batsukh",
    "mobile": "92******",
    "email": "solongo.batsukh@outlook.com"
  },
  {
    "id": 9,
    "firstName": "Zolzaya",
    "lastName": "Erkhembayar",
    "mobile": "97******",
    "email": "zolzaya.e@gmail.com"
  },
  {
    "id": 10,
    "firstName": "Temuulen",
    "lastName": "Otgonbayar",
    "mobile": "91******",
    "email": "temuulen.otgon@gmail.com"
  },
  {
    "id": 11,
    "firstName": "Bayarjargal",
    "lastName": "Dashdorj",
    "mobile": "89******",
    "email": "bayar.dash@example.com"
  },
  {
    "id": 12,
    "firstName": "Anujin",
    "lastName": "Bilegt",
    "mobile": "87******",
    "email": "anujin.bilegt@mail.mn"
  },
  {
    "id": 13,
    "firstName": "Munkhbat",
    "lastName": "Enkhbayar",
    "mobile": "93******",
    "email": "munkh.enkh@gmail.com"
  },
  {
    "id": 14,
    "firstName": "Erdene",
    "lastName": "Naranbaatar",
    "mobile": "84******",
    "email": "erdene.naran@info.com"
  },
  {
    "id": 15,
    "firstName": "Khulan",
    "lastName": "Batjargal",
    "mobile": "86******",
    "email": "khulan.bj@gmail.com"
  },
  {
    "id": 16,
    "firstName": "Tegshjargal",
    "lastName": "Bold",
    "mobile": "98******",
    "email": "tegsh.bold@example.com"
  },
  {
    "id": 17,
    "firstName": "Sarnai",
    "lastName": "Enkhbat",
    "mobile": "83******",
    "email": "sarnai.enkh@domain.mn"
  },
  {
    "id": 18,
    "firstName": "Bilguun",
    "lastName": "Dashzeveg",
    "mobile": "82******",
    "email": "bilguun.dz@yahoo.com"
  },
  {
    "id": 19,
    "firstName": "Narantuya",
    "lastName": "Javkhlan",
    "mobile": "81******",
    "email": "naraa.javkhlan@mail.com"
  },
  {
    "id": 20,
    "firstName": "Tumen",
    "lastName": "Bayarsaikhan",
    "mobile": "80******",
    "email": "tumen.bayarsaikhan@gmail.com"
  }
]
